{"text": "The agreement in question involves number in nouns and reflexive pronouns and is syntactic rather than semantic in nature because grammatical number in English , like grammatical gender in languages such as French , is partly arbitrary .", "spo_list": [{"predicate": "Conjunction", "subject": "nouns", "subject_type": "OtherScientificTerm", "object": "reflexive pronouns", "object_type": "OtherScientificTerm"}, {"predicate": "Feature-of", "subject": "grammatical gender", "subject_type": "OtherScientificTerm", "object": "languages", "object_type": "Material"}, {"predicate": "Hyponym-of", "subject": "French", "subject_type": "Material", "object": "languages", "object_type": "Material"}]}
{"text": "In this paper , a novel method to learn the intrinsic object structure for robust visual tracking is proposed .", "spo_list": [{"predicate": "Used-for", "subject": "method", "subject_type": "Method", "object": "intrinsic object structure", "object_type": "OtherScientificTerm"}, {"predicate": "Used-for", "subject": "intrinsic object structure", "subject_type": "OtherScientificTerm", "object": "robust visual tracking", "object_type": "Task"}]}
{"text": "The basic assumption is that the parameterized object state lies on a low dimensional manifold and can be learned from training data .", "spo_list": [{"predicate": "Feature-of", "subject": "low dimensional manifold", "subject_type": "OtherScientificTerm", "object": "parameterized object state", "object_type": "OtherScientificTerm"}]}
